llama_index/packs/multidoc_autoretrieval/__init__.py
llama_index/packs/multidoc_autoretrieval/base.py
llama_index_packs_multidoc_autoretrieval-0.4.1.dist-info/METADATA
llama_index_packs_multidoc_autoretrieval-0.4.1.dist-info/WHEEL
llama_index_packs_multidoc_autoretrieval-0.4.1.dist-info/licenses/LICENSE
llama_index_packs_multidoc_autoretrieval-0.4.1.dist-info/RECORD
