Metadata-Version: 2.4
Name: llama-index-packs-multidoc-autoretrieval
Version: 0.4.1
Summary: llama-index packs multidoc_autoretrieval integration
Author-email: Your Name <you@example.com>
Maintainer: jerryjliu
License-Expression: MIT
License-File: LICENSE
Keywords: autoretrieval,document,multi,multidoc,retrieval
Requires-Python: <4.0,>=3.9
Requires-Dist: llama-index-core<0.15,>=0.13.0
Requires-Dist: llama-index-llms-openai<0.6,>=0.5.0
Requires-Dist: llama-index-vector-stores-weaviate<2,>=1.2.0
